<archimate:ArchimateDiagramModel
    xmlns:xsi="http://www.w3.org/2001/XMLSchema-instance"
    xmlns:archimate="http://www.archimatetool.com/archimate"
    name="Referentiecomponenten Omnichannel (totaal overzicht)"
    id="id-bdb32fdeb97844f39d387df71fe50206">
  <children
      xsi:type="archimate:DiagramModelGroup"
      id="id-95f2906f955e41238f037c75e651dedf"
      name="Referentiecomponenten ondersteunend bij het aanbieden van kanalen"
      textAlignment="1"
      fillColor="#ffffff">
    <bounds
        x="12"
        y="12"
        width="1284"
        height="325"/>
    <children
        xsi:type="archimate:DiagramModelArchimateObject"
        id="id-2aa0ce2c8efb4d8785efd26681903fa1"
        fillColor="#daeef3"
        textPosition="1"
        type="1">
      <bounds
          x="336"
          y="36"
          width="144"
          height="55"/>
      <archimateElement
          xsi:type="archimate:ApplicationComponent"
          href="ApplicationComponent_id-38049e68870e2a326bff71eeab5b5c64.xml#id-38049e68870e2a326bff71eeab5b5c64"/>
    </children>
    <children
        xsi:type="archimate:DiagramModelArchimateObject"
        id="id-f72e19dc7e754540b9a27ccca88fe949"
        fillColor="#daeef3"
        textPosition="1"
        type="1">
      <bounds
          x="23"
          y="105"
          width="144"
          height="55"/>
      <archimateElement
          xsi:type="archimate:ApplicationComponent"
          href="ApplicationComponent_id-8092f0079af7f202e220207d070d5633.xml#id-8092f0079af7f202e220207d070d5633"/>
    </children>
    <children
        xsi:type="archimate:DiagramModelArchimateObject"
        id="id-4eefa1c6e3814ff28c5b981baab5e293"
        fillColor="#daeef3"
        textPosition="1"
        type="1">
      <bounds
          x="492"
          y="105"
          width="144"
          height="55"/>
      <archimateElement
          xsi:type="archimate:ApplicationComponent"
          href="ApplicationComponent_id-1ce8a1c31a2d1677084a9864d75c57a5.xml#id-1ce8a1c31a2d1677084a9864d75c57a5"/>
    </children>
    <children
        xsi:type="archimate:DiagramModelArchimateObject"
        id="id-a64fcd1624ce4f33a17fb009252464a2"
        fillColor="#daeef3"
        textPosition="1"
        type="1">
      <bounds
          x="648"
          y="105"
          width="144"
          height="55"/>
      <archimateElement
          xsi:type="archimate:ApplicationComponent"
          href="ApplicationComponent_id-b114ed78edb152c1d1a5dec1203636f3.xml#id-b114ed78edb152c1d1a5dec1203636f3"/>
    </children>
    <children
        xsi:type="archimate:DiagramModelArchimateObject"
        id="id-db76ad5979a64a1f91e931bde6366bcf"
        fillColor="#daeef3"
        textPosition="1"
        type="1">
      <bounds
          x="804"
          y="36"
          width="144"
          height="55"/>
      <archimateElement
          xsi:type="archimate:ApplicationComponent"
          href="ApplicationComponent_id-7dc0f6beac6b4d150fad8c1adcc1f028.xml#id-7dc0f6beac6b4d150fad8c1adcc1f028"/>
    </children>
    <children
        xsi:type="archimate:DiagramModelArchimateObject"
        id="id-fe8fa69a48504a4d9902aca328e1c81b"
        fillColor="#daeef3"
        textPosition="1"
        type="1">
      <bounds
          x="1115"
          y="36"
          width="144"
          height="55"/>
      <archimateElement
          xsi:type="archimate:ApplicationComponent"
          href="ApplicationComponent_id-ccaa99ef2a50643bcbf378fa3a895b9d.xml#id-ccaa99ef2a50643bcbf378fa3a895b9d"/>
    </children>
    <children
        xsi:type="archimate:DiagramModelArchimateObject"
        id="id-65481802c5ee457980adb26bf4042885"
        fillColor="#daeef3"
        textPosition="1"
        type="1">
      <bounds
          x="648"
          y="36"
          width="144"
          height="55"/>
      <archimateElement
          xsi:type="archimate:ApplicationComponent"
          href="ApplicationComponent_id-422ea41ad3fb040c6bd8d9d69cd2a7b3.xml#id-422ea41ad3fb040c6bd8d9d69cd2a7b3"/>
    </children>
    <children
        xsi:type="archimate:DiagramModelArchimateObject"
        id="id-1f8785865e0543cfa2dfba69d848e217"
        fillColor="#daeef3"
        textPosition="1"
        type="1">
      <bounds
          x="959"
          y="36"
          width="144"
          height="55"/>
      <archimateElement
          xsi:type="archimate:ApplicationComponent"
          href="ApplicationComponent_id-c41ed2b18e3fc00484d938d512f31989.xml#id-c41ed2b18e3fc00484d938d512f31989"/>
    </children>
    <children
        xsi:type="archimate:DiagramModelArchimateObject"
        id="id-9c67a44f58594fd0925f54de139edb33"
        fillColor="#daeef3"
        textPosition="1"
        type="1">
      <bounds
          x="180"
          y="36"
          width="144"
          height="55"/>
      <archimateElement
          xsi:type="archimate:ApplicationComponent"
          href="ApplicationComponent_id-06a16e6b97154de58a03f06589bd3940.xml#id-06a16e6b97154de58a03f06589bd3940"/>
    </children>
    <children
        xsi:type="archimate:DiagramModelArchimateObject"
        id="id-583d2cc79e58493e8d0b3ece8b790af8"
        fillColor="#daeef3"
        textPosition="1"
        type="1">
      <bounds
          x="23"
          y="36"
          width="144"
          height="55"/>
      <archimateElement
          xsi:type="archimate:ApplicationComponent"
          href="ApplicationComponent_id-451de2f1e9a7478ea7b8a4c0ef205ca4.xml#id-451de2f1e9a7478ea7b8a4c0ef205ca4"/>
    </children>
    <children
        xsi:type="archimate:DiagramModelArchimateObject"
        id="id-097ac437a34741278656668896b0b8ed"
        fillColor="#daeef3"
        textPosition="1"
        type="1">
      <bounds
          x="492"
          y="36"
          width="144"
          height="55"/>
      <archimateElement
          xsi:type="archimate:ApplicationComponent"
          href="ApplicationComponent_id-bfe74ba85ab04af9a991ac3df2d75c27.xml#id-bfe74ba85ab04af9a991ac3df2d75c27"/>
    </children>
    <children
        xsi:type="archimate:DiagramModelArchimateObject"
        id="id-9e5f94984802408f93f472d1929c8867"
        fillColor="#daeef3"
        textPosition="1"
        type="1">
      <bounds
          x="336"
          y="105"
          width="144"
          height="55"/>
      <archimateElement
          xsi:type="archimate:ApplicationComponent"
          href="ApplicationComponent_id-e30d426b268520af43cad71d2b80a495.xml#id-e30d426b268520af43cad71d2b80a495"/>
    </children>
    <children
        xsi:type="archimate:DiagramModelArchimateObject"
        id="id-255d833bd1624969b3034e62b69e5580"
        fillColor="#daeef3"
        textPosition="1"
        type="1">
      <bounds
          x="180"
          y="105"
          width="144"
          height="55"/>
      <archimateElement
          xsi:type="archimate:ApplicationComponent"
          href="ApplicationComponent_id-9d3c2f52104d4bfa61159999e9278094.xml#id-9d3c2f52104d4bfa61159999e9278094"/>
    </children>
    <children
        xsi:type="archimate:DiagramModelArchimateObject"
        id="id-1f8ccf3505d245ddbf28655d68805628"
        fillColor="#daeef3"
        textPosition="1"
        type="1">
      <bounds
          x="959"
          y="105"
          width="144"
          height="55"/>
      <archimateElement
          xsi:type="archimate:ApplicationComponent"
          href="ApplicationComponent_id-78c011a6d48d281e0dae88ccd3b9cb4f.xml#id-78c011a6d48d281e0dae88ccd3b9cb4f"/>
    </children>
    <children
        xsi:type="archimate:DiagramModelArchimateObject"
        id="id-831c0e58ee8e4a078361b65cc7e0b4ef"
        fillColor="#daeef3"
        textPosition="1"
        type="1">
      <bounds
          x="804"
          y="105"
          width="144"
          height="55"/>
      <archimateElement
          xsi:type="archimate:ApplicationComponent"
          href="ApplicationComponent_id-b12cd80da81897736ac8148239f41d6f.xml#id-b12cd80da81897736ac8148239f41d6f"/>
    </children>
    <children
        xsi:type="archimate:DiagramModelArchimateObject"
        id="id-5a097f18d64a49609d6228de7bfabbad"
        fillColor="#daeef3"
        textPosition="1"
        type="1">
      <bounds
          x="23"
          y="180"
          width="144"
          height="55"/>
      <archimateElement
          xsi:type="archimate:ApplicationComponent"
          href="ApplicationComponent_id-31dc887ec9509cd06223351bfce26e2e.xml#id-31dc887ec9509cd06223351bfce26e2e"/>
    </children>
    <children
        xsi:type="archimate:DiagramModelArchimateObject"
        id="id-caea0c292bca4934a0e4ed8fab99424c"
        fillColor="#daeef3"
        textPosition="1"
        type="1">
      <bounds
          x="180"
          y="180"
          width="144"
          height="55"/>
      <archimateElement
          xsi:type="archimate:ApplicationComponent"
          href="ApplicationComponent_id-2f6b735185a942f7bebf069bc3e4d213.xml#id-2f6b735185a942f7bebf069bc3e4d213"/>
    </children>
    <children
        xsi:type="archimate:DiagramModelArchimateObject"
        id="id-c7a56b3f6406453eae14ab0a892feb2d"
        fillColor="#daeef3"
        textPosition="1"
        type="1">
      <bounds
          x="336"
          y="180"
          width="144"
          height="55"/>
      <archimateElement
          xsi:type="archimate:ApplicationComponent"
          href="ApplicationComponent_id-6c6e9be554145dcaa2387b0e3141005f.xml#id-6c6e9be554145dcaa2387b0e3141005f"/>
    </children>
    <children
        xsi:type="archimate:DiagramModelArchimateObject"
        id="id-f722821b4b754d4d89d41e2ac2074a67"
        fillColor="#daeef3"
        textPosition="1"
        type="1">
      <bounds
          x="648"
          y="180"
          width="144"
          height="55"/>
      <archimateElement
          xsi:type="archimate:ApplicationComponent"
          href="ApplicationComponent_id-69b8fac774cb0dd97b0d899297810cdd.xml#id-69b8fac774cb0dd97b0d899297810cdd"/>
    </children>
    <children
        xsi:type="archimate:DiagramModelArchimateObject"
        id="id-4f2eee1dff8446cbbb9fb7cf3f3e8447"
        fillColor="#daeef3"
        textPosition="1"
        type="1">
      <bounds
          x="804"
          y="180"
          width="144"
          height="55"/>
      <archimateElement
          xsi:type="archimate:ApplicationComponent"
          href="ApplicationComponent_id-ece860fde85d98964456305805dd7f2f.xml#id-ece860fde85d98964456305805dd7f2f"/>
    </children>
    <children
        xsi:type="archimate:DiagramModelArchimateObject"
        id="id-a852eebfd79d403baa0ebf8376e50b83"
        fillColor="#daeef3"
        textPosition="1"
        type="1">
      <bounds
          x="959"
          y="180"
          width="144"
          height="55"/>
      <archimateElement
          xsi:type="archimate:ApplicationComponent"
          href="ApplicationComponent_id-4e259a05612c1d0003a9664f5bb8f7da.xml#id-4e259a05612c1d0003a9664f5bb8f7da"/>
    </children>
    <children
        xsi:type="archimate:DiagramModelArchimateObject"
        id="id-a071f4e967464cbfa3cd1e9e8caba68f"
        fillColor="#daeef3"
        textPosition="1"
        type="1">
      <bounds
          x="23"
          y="252"
          width="144"
          height="55"/>
      <archimateElement
          xsi:type="archimate:ApplicationComponent"
          href="ApplicationComponent_id-c466e223307de2b762dd52c343c0573f.xml#id-c466e223307de2b762dd52c343c0573f"/>
    </children>
    <children
        xsi:type="archimate:DiagramModelArchimateObject"
        id="id-c4bdcffef2944fbf88ca47e6b44a3af5"
        fillColor="#daeef3"
        textPosition="1"
        type="1">
      <bounds
          x="180"
          y="252"
          width="144"
          height="55"/>
      <archimateElement
          xsi:type="archimate:ApplicationComponent"
          href="ApplicationComponent_id-b227a9af2bc85c214a7d246e186a1d13.xml#id-b227a9af2bc85c214a7d246e186a1d13"/>
    </children>
    <children
        xsi:type="archimate:DiagramModelArchimateObject"
        id="id-7f247a5e6ddb44f7839c915f190233d5"
        fillColor="#daeef3"
        textPosition="1"
        type="1">
      <bounds
          x="336"
          y="252"
          width="144"
          height="55"/>
      <archimateElement
          xsi:type="archimate:ApplicationComponent"
          href="ApplicationComponent_id-a040db2a70ea2e91ccfba034efae3e5a.xml#id-a040db2a70ea2e91ccfba034efae3e5a"/>
    </children>
    <children
        xsi:type="archimate:DiagramModelArchimateObject"
        id="id-82fbe49c400c4192a13b61eca56415cb"
        fillColor="#daeef3"
        textPosition="1"
        type="1">
      <bounds
          x="492"
          y="180"
          width="144"
          height="55"/>
      <archimateElement
          xsi:type="archimate:ApplicationComponent"
          href="ApplicationComponent_id-2567e60833f2679428e015f5a0e66115.xml#id-2567e60833f2679428e015f5a0e66115"/>
    </children>
    <children
        xsi:type="archimate:DiagramModelArchimateObject"
        id="id-340210f346de45abba591ca6d7536090"
        fillColor="#daeef3"
        textPosition="1"
        type="1">
      <bounds
          x="1115"
          y="180"
          width="144"
          height="55"/>
      <archimateElement
          xsi:type="archimate:ApplicationComponent"
          href="ApplicationComponent_id-ce0363ea43b714cfebb56a50c8800409.xml#id-ce0363ea43b714cfebb56a50c8800409"/>
    </children>
    <children
        xsi:type="archimate:DiagramModelArchimateObject"
        id="id-504f68760d41475b977b1a1f2fd423a8"
        fillColor="#daeef3"
        textPosition="1"
        type="1">
      <bounds
          x="1115"
          y="105"
          width="144"
          height="55"/>
      <archimateElement
          xsi:type="archimate:ApplicationComponent"
          href="ApplicationComponent_id-1775dccf470945468995147178eeea17.xml#id-1775dccf470945468995147178eeea17"/>
    </children>
  </children>
  <children
      xsi:type="archimate:DiagramModelGroup"
      id="id-670cefbae94a4554b5c7d6bd94df75fd"
      name="Referentiecomponenten 'Data integratie'"
      textAlignment="1"
      fillColor="#ffffff">
    <bounds
        x="12"
        y="624"
        width="1284"
        height="121"/>
    <children
        xsi:type="archimate:DiagramModelArchimateObject"
        id="id-54654484f4c1423c9b6e0e03a477d68e"
        fillColor="#daeef3"
        textPosition="1"
        type="1">
      <bounds
          x="228"
          y="36"
          width="194"
          height="55"/>
      <archimateElement
          xsi:type="archimate:ApplicationComponent"
          href="ApplicationComponent_id-40805a92105dd327c532ebf2eca147c5.xml#id-40805a92105dd327c532ebf2eca147c5"/>
    </children>
    <children
        xsi:type="archimate:DiagramModelArchimateObject"
        id="id-804fa52fd9c64544820f3b3ac1e43bef"
        fillColor="#daeef3"
        textPosition="1"
        type="1">
      <bounds
          x="444"
          y="36"
          width="194"
          height="55"/>
      <archimateElement
          xsi:type="archimate:ApplicationComponent"
          href="ApplicationComponent_id-0ed38c14fab24ae8b6bf4ad0d91faac9.xml#id-0ed38c14fab24ae8b6bf4ad0d91faac9"/>
    </children>
    <children
        xsi:type="archimate:DiagramModelArchimateObject"
        id="id-10dde3957aae4c9b92846c01e4034621"
        fillColor="#daeef3"
        textPosition="1"
        type="1">
      <bounds
          x="660"
          y="36"
          width="194"
          height="55"/>
      <archimateElement
          xsi:type="archimate:ApplicationComponent"
          href="ApplicationComponent_id-cfbaf91238e14ff3a90d925a129c7f64.xml#id-cfbaf91238e14ff3a90d925a129c7f64"/>
    </children>
    <children
        xsi:type="archimate:DiagramModelArchimateObject"
        id="id-dc10748e59fb4bca8d0e237d2436e23b"
        fillColor="#daeef3"
        textPosition="1"
        type="1">
      <bounds
          x="1080"
          y="36"
          width="194"
          height="55"/>
      <archimateElement
          xsi:type="archimate:ApplicationComponent"
          href="ApplicationComponent_id-c6dbb637ad82c12a3c6634c6560bddb4.xml#id-c6dbb637ad82c12a3c6634c6560bddb4"/>
    </children>
    <children
        xsi:type="archimate:DiagramModelArchimateObject"
        id="id-c5a6a6ba01034a3682b962bbaa2ba653"
        fillColor="#daeef3"
        textPosition="1"
        type="1">
      <bounds
          x="876"
          y="36"
          width="194"
          height="55"/>
      <archimateElement
          xsi:type="archimate:ApplicationComponent"
          href="ApplicationComponent_id-e386ff94e7b499fbd6f675ac9eb1572e.xml#id-e386ff94e7b499fbd6f675ac9eb1572e"/>
    </children>
    <children
        xsi:type="archimate:DiagramModelArchimateObject"
        id="id-04874ff3ef2b41a2b76f9bb9aa5f224d"
        fillColor="#daeef3"
        textPosition="1"
        type="1">
      <bounds
          x="12"
          y="36"
          width="194"
          height="55"/>
      <archimateElement
          xsi:type="archimate:ApplicationComponent"
          href="ApplicationComponent_id-b0dd3a0f554804e16776943b9b3a787c.xml#id-b0dd3a0f554804e16776943b9b3a787c"/>
    </children>
  </children>
  <children
      xsi:type="archimate:DiagramModelGroup"
      id="id-cf2e4fd84da244a8ad7af8b198f39f7b"
      name="Referentiecomponenten ondersteunend bij aanbieden data"
      textAlignment="1"
      fillColor="#ffffff">
    <bounds
        x="12"
        y="756"
        width="1284"
        height="241"/>
    <children
        xsi:type="archimate:DiagramModelArchimateObject"
        id="id-2e03e2b82f3841ada15710d966ce1cdf"
        fillColor="#daeef3"
        textPosition="1"
        type="1">
      <bounds
          x="227"
          y="36"
          width="194"
          height="55"/>
      <archimateElement
          xsi:type="archimate:ApplicationComponent"
          href="ApplicationComponent_id-9c861a527fd0bf955d7cc4318de475c3.xml#id-9c861a527fd0bf955d7cc4318de475c3"/>
    </children>
    <children
        xsi:type="archimate:DiagramModelArchimateObject"
        id="id-7a5a0662c7724122b2c781fbb5a15ef7"
        fillColor="#daeef3"
        textPosition="1"
        type="1">
      <bounds
          x="12"
          y="36"
          width="194"
          height="55"/>
      <archimateElement
          xsi:type="archimate:ApplicationComponent"
          href="ApplicationComponent_id-a0f9f83e8593688e3af4d0562f217881.xml#id-a0f9f83e8593688e3af4d0562f217881"/>
    </children>
    <children
        xsi:type="archimate:DiagramModelArchimateObject"
        id="id-d9725c7630994fd2864a1b0fa46e4f3c"
        fillColor="#daeef3"
        textPosition="1"
        type="1">
      <bounds
          x="444"
          y="108"
          width="194"
          height="55"/>
      <archimateElement
          xsi:type="archimate:ApplicationComponent"
          href="ApplicationComponent_id-b4ba595f776735224751ffc8e761ae60.xml#id-b4ba595f776735224751ffc8e761ae60"/>
    </children>
    <children
        xsi:type="archimate:DiagramModelArchimateObject"
        id="id-23665f1bcd854b15a4c4b4d3dbb810db"
        fillColor="#daeef3"
        textPosition="1"
        type="1">
      <bounds
          x="444"
          y="36"
          width="194"
          height="55"/>
      <archimateElement
          xsi:type="archimate:ApplicationComponent"
          href="ApplicationComponent_id-c466e223307de2b762dd52c343c0573f.xml#id-c466e223307de2b762dd52c343c0573f"/>
    </children>
    <children
        xsi:type="archimate:DiagramModelArchimateObject"
        id="id-3a1b0f202aca46659428a32213056db6"
        fillColor="#daeef3"
        textPosition="1"
        type="1">
      <bounds
          x="1080"
          y="36"
          width="194"
          height="55"/>
      <archimateElement
          xsi:type="archimate:ApplicationComponent"
          href="ApplicationComponent_id-d09413ab6905c56d1628eff1460e936e.xml#id-d09413ab6905c56d1628eff1460e936e"/>
    </children>
    <children
        xsi:type="archimate:DiagramModelArchimateObject"
        id="id-fb974b45708b4319a5622dc869012ed6"
        fillColor="#daeef3"
        textPosition="1"
        type="1">
      <bounds
          x="227"
          y="108"
          width="194"
          height="55"/>
      <archimateElement
          xsi:type="archimate:ApplicationComponent"
          href="ApplicationComponent_id-998caa24799a47ae82ec5bc9665a2a3e.xml#id-998caa24799a47ae82ec5bc9665a2a3e"/>
    </children>
    <children
        xsi:type="archimate:DiagramModelArchimateObject"
        id="id-9db9fc99be1a46a680a0f17a7a71670a"
        fillColor="#daeef3"
        textPosition="1"
        type="1">
      <bounds
          x="876"
          y="36"
          width="194"
          height="55"/>
      <archimateElement
          xsi:type="archimate:ApplicationComponent"
          href="ApplicationComponent_id-f3bffd3f8fce63c5ad8314ce103e4881.xml#id-f3bffd3f8fce63c5ad8314ce103e4881"/>
    </children>
    <children
        xsi:type="archimate:DiagramModelArchimateObject"
        id="id-e610096110c34a3abcc0dfbd104d738a"
        fillColor="#daeef3"
        textPosition="1"
        type="1">
      <bounds
          x="876"
          y="107"
          width="194"
          height="55"/>
      <archimateElement
          xsi:type="archimate:ApplicationComponent"
          href="ApplicationComponent_id-941f4621a78771f27a8f3778c3278dd2.xml#id-941f4621a78771f27a8f3778c3278dd2"/>
    </children>
    <children
        xsi:type="archimate:DiagramModelArchimateObject"
        id="id-63cb09256c0e4d66b27a3461b223e942"
        fillColor="#daeef3"
        textPosition="1"
        type="1">
      <bounds
          x="1080"
          y="108"
          width="194"
          height="55"/>
      <archimateElement
          xsi:type="archimate:ApplicationComponent"
          href="ApplicationComponent_id-c86193f0f6924d67acae1e22e6248dc0.xml#id-c86193f0f6924d67acae1e22e6248dc0"/>
    </children>
    <children
        xsi:type="archimate:DiagramModelArchimateObject"
        id="id-2120b85494e543138234b5a5804a3cc9"
        fillColor="#daeef3"
        textPosition="1"
        type="1">
      <bounds
          x="660"
          y="108"
          width="194"
          height="55"/>
      <archimateElement
          xsi:type="archimate:ApplicationComponent"
          href="ApplicationComponent_id-3d9a4259204847f1a1a1470fe8e16517.xml#id-3d9a4259204847f1a1a1470fe8e16517"/>
    </children>
    <children
        xsi:type="archimate:DiagramModelArchimateObject"
        id="id-ad84c915cace448ca8e47d5c5ab59f84"
        fillColor="#daeef3"
        textPosition="1"
        type="1">
      <bounds
          x="227"
          y="176"
          width="194"
          height="55"/>
      <archimateElement
          xsi:type="archimate:ApplicationComponent"
          href="ApplicationComponent_id-c5fa06b1a6094609a39dfda56fe2ea33.xml#id-c5fa06b1a6094609a39dfda56fe2ea33"/>
    </children>
    <children
        xsi:type="archimate:DiagramModelArchimateObject"
        id="id-b8e2b3e34caa48d2aecf6f668afbaa7a"
        fillColor="#daeef3"
        textPosition="1"
        type="1">
      <bounds
          x="12"
          y="107"
          width="194"
          height="55"/>
      <archimateElement
          xsi:type="archimate:ApplicationComponent"
          href="ApplicationComponent_id-57f5270a0dfc463b80f1037eaea56cac.xml#id-57f5270a0dfc463b80f1037eaea56cac"/>
    </children>
    <children
        xsi:type="archimate:DiagramModelArchimateObject"
        id="id-f9d558fd9d1342d2a6d091bcd9bab989"
        fillColor="#daeef3"
        textPosition="1"
        type="1">
      <bounds
          x="660"
          y="36"
          width="194"
          height="55"/>
      <archimateElement
          xsi:type="archimate:ApplicationComponent"
          href="ApplicationComponent_id-f1331e968ae746a8a84889793dee750b.xml#id-f1331e968ae746a8a84889793dee750b"/>
    </children>
    <children
        xsi:type="archimate:DiagramModelArchimateObject"
        id="id-a7aff1b2b5bd45059835039081acbb5a"
        fillColor="#daeef3"
        textPosition="1"
        type="1">
      <bounds
          x="12"
          y="176"
          width="194"
          height="55"/>
      <archimateElement
          xsi:type="archimate:ApplicationComponent"
          href="ApplicationComponent_id-077904e68d3b4e07a5141fc92756a6cb.xml#id-077904e68d3b4e07a5141fc92756a6cb"/>
    </children>
  </children>
  <children
      xsi:type="archimate:DiagramModelGroup"
      id="id-e7ebeb96edf04b1caca6838e7428b42e"
      name="Referentiecomponenten 'Processen'"
      textAlignment="1"
      fillColor="#ffffff">
    <bounds
        x="12"
        y="480"
        width="1284"
        height="133"/>
    <children
        xsi:type="archimate:DiagramModelArchimateObject"
        id="id-08a76f422d03467095079cf1bbea5acd"
        fillColor="#daeef3"
        textPosition="1"
        type="1">
      <bounds
          x="444"
          y="48"
          width="194"
          height="55"/>
      <archimateElement
          xsi:type="archimate:ApplicationComponent"
          href="ApplicationComponent_id-0ad424f136472fb55c6444798cd244cf.xml#id-0ad424f136472fb55c6444798cd244cf"/>
    </children>
    <children
        xsi:type="archimate:DiagramModelArchimateObject"
        id="id-66df37293c86448fbd22ee9b613ae964"
        fillColor="#daeef3"
        textPosition="1"
        type="1">
      <bounds
          x="876"
          y="48"
          width="194"
          height="55"/>
      <archimateElement
          xsi:type="archimate:ApplicationComponent"
          href="ApplicationComponent_id-8880802a601caa48c4d960ab6614a001.xml#id-8880802a601caa48c4d960ab6614a001"/>
    </children>
    <children
        xsi:type="archimate:DiagramModelArchimateObject"
        id="id-2d7c44c005f54b3f81a631fe1cdc1325"
        fillColor="#daeef3"
        textPosition="1"
        type="1">
      <bounds
          x="12"
          y="48"
          width="194"
          height="55"/>
      <archimateElement
          xsi:type="archimate:ApplicationComponent"
          href="ApplicationComponent_id-a59fce48622962f4c1a7504aa69a65c6.xml#id-a59fce48622962f4c1a7504aa69a65c6"/>
    </children>
    <children
        xsi:type="archimate:DiagramModelArchimateObject"
        id="id-26d0f711912d4b68bdd2ae0f5fc753a6"
        fillColor="#daeef3"
        textPosition="1"
        type="1">
      <bounds
          x="660"
          y="48"
          width="192"
          height="55"/>
      <archimateElement
          xsi:type="archimate:ApplicationComponent"
          href="ApplicationComponent_id-dc7276bd64ae22f86bac04fc9b9ea480.xml#id-dc7276bd64ae22f86bac04fc9b9ea480"/>
    </children>
    <children
        xsi:type="archimate:DiagramModelArchimateObject"
        id="id-b608511e8f85498682824b91b9a16f44"
        fillColor="#daeef3"
        textPosition="1"
        type="1">
      <bounds
          x="228"
          y="48"
          width="192"
          height="55"/>
      <archimateElement
          xsi:type="archimate:ApplicationComponent"
          href="ApplicationComponent_id-1588197a02f651959156b97286d98150.xml#id-1588197a02f651959156b97286d98150"/>
    </children>
  </children>
  <children
      xsi:type="archimate:DiagramModelGroup"
      id="id-3914b1d16813456dbb6d4c682890d69d"
      name="De referentiecomponenten als kern van omnichannel"
      textAlignment="1"
      fillColor="#ffffff">
    <bounds
        x="12"
        y="348"
        width="1284"
        height="120"/>
    <children
        xsi:type="archimate:DiagramModelArchimateObject"
        id="id-650f238eb3984d8ea4c6c53678758921"
        fillColor="#daeef3"
        textPosition="1"
        type="1">
      <bounds
          x="960"
          y="48"
          width="313"
          height="55"/>
      <archimateElement
          xsi:type="archimate:ApplicationComponent"
          href="ApplicationComponent_id-1e923a5a0d5b9759ad142bd8e37595b4.xml#id-1e923a5a0d5b9759ad142bd8e37595b4"/>
    </children>
    <children
        xsi:type="archimate:DiagramModelArchimateObject"
        id="id-c87b95674bd746c0a14ae2ca1ec21331"
        fillColor="#daeef3"
        textPosition="1"
        type="1">
      <bounds
          x="12"
          y="48"
          width="936"
          height="55"/>
      <archimateElement
          xsi:type="archimate:ApplicationComponent"
          href="ApplicationComponent_id-fe767ca0f7fb44ef97647d7d65811ebc.xml#id-fe767ca0f7fb44ef97647d7d65811ebc"/>
    </children>
  </children>
</archimate:ArchimateDiagramModel>
